MANIFEST.in
README
requirements.txt
setup.py
py3mqi.egg-info/PKG-INFO
py3mqi.egg-info/SOURCES.txt
py3mqi.egg-info/dependency_links.txt
py3mqi.egg-info/top_level.txt
pymqi/CMQC.py
pymqi/CMQCFC.py
pymqi/CMQXC.py
pymqi/CMQZC.py
pymqi/__init__.py
pymqi/pymqe.c