Metadata-Version: 1.1
Name: py3mqi
Version: 1.6.0
Summary: Python IBM MQI Extension for WebSphere MQ (formerly known as MQSeries).
Home-page: https://pythonhosted.org/pymqi/
Author: Reinhard Pilz
Author-email: reinhard.pilz@gmail.com
License: Python Software Foundation License
Download-URL: https://github.com/Dynatrace-Reinhard-Pilz/pymqi3
Keywords: pymqi WebSphere MQ WMQ MQSeries IBM middleware messaging queueing asynchronous SOA EAI ESB integration
Platform: Linux
Classifier: Development Status :: 3 - Alpha
Classifier: License :: OSI Approved :: Python Software Foundation License
Classifier: Intended Audience :: Developers
Classifier: Natural Language :: English
Classifier: Operating System :: POSIX :: Linux
Classifier: Programming Language :: C
Classifier: Programming Language :: Python :: 3.5
Classifier: Topic :: Software Development :: Libraries :: Python Modules
Classifier: Topic :: Software Development :: Object Brokering
